[
    {
        "firstname": "Aïda",
        "lastname": "Loemba"
    },
    {
        "firstname": "Amruta",
        "lastname": "Karanjekar"
    },
    {
        "firstname": "Ana",
        "lastname": "Durguz"
    },
    {
        "firstname": "Elko",
        "lastname": "Lemiso"
    },
    {
        "firstname": "Melanie",
        "lastname": "Nachef"
    },
    {
        "firstname": "Nardo",
        "lastname": "Kraaijeveld"
    },
    {
        "firstname": "Nienke",
        "lastname": "Westdijk"
    },
    {
        "firstname": "Varun",
        "lastname": "Kumar Chalotra"
    }
]